{
  "geode": "4.2.0",
  "version": "v1.3.0",
  "gd": {
    "win": "2.2074",
    "android": "2.2074",
    "mac": "2.2074"
  },
  "id": "itzkiba.elegant_rankings",
  "name": "Profile Rankings",
  "developer": "ItzKiba",
  "description": "Adds nicer looking rankings to profile pages.",
  "dependencies": {
      "geode.node-ids": "1.19.0"
  },
  "resources": {
    "spritesheets": {
      "ER_SpriteSheet": ["resources/*.png"]
    }
  },
  "repository": "https://github.com/ItzKiba/ProfileRankings",
  "tags": ["online", "enhancement", "interface"]
}